LICENSE
MANIFEST.in
README.md
requirements.txt
setup.cfg
setup.py
django_mp_services.egg-info/PKG-INFO
django_mp_services.egg-info/SOURCES.txt
django_mp_services.egg-info/dependency_links.txt
django_mp_services.egg-info/top_level.txt
services/__init__.py
services/admin.py
services/forms.py
services/managers.py
services/models.py
services/querysets.py
services/urls.py
services/views.py
services/locale/ru/LC_MESSAGES/django.po
services/locale/uk/LC_MESSAGES/django.mo
services/locale/uk/LC_MESSAGES/django.po
services/migrations/0001_initial.py
services/migrations/__init__.py
services/templates/services/item.html
services/templates/services/print-service-items.html
services/templates/services/print-services-table.html
services/templates/services/print-services.html
services/templates/services/report.html
services/templates/services/service-items.html