Metadata-Version: 1.1
Name: django-mp-services
Version: 0.4
Summary: Django services app
Home-page: https://github.com/pmaigutyak/mp-services
Author: Paul Maigutyak
Author-email: pmaigutyak@gmail.com
License: MIT
Download-URL: https://github.com/pmaigutyak/mp-services/archive/0.4.tar.gz
Platform: UNKNOWN
